Workbook

Sheet 01_Audit_Planning
A1: Jarir Audit Simulation 2025 — Audit Planning
A2: Educational external audit simulation | Jarir Marketing Company | Amounts in SAR '000 unless stated
A4: A. Engagement Information
A5: Project name | B5: Jarir Audit Simulation 2025
A6: Entity | B6: Jarir Marketing Company (Jarir Bookstore)
A7: Reporting period | B7: Year ended 31 December 2025
A8: Engagement type | B8: Educational external audit simulation
A9: Prepared by | B9: Hanan aldalbahi
A10: Preparation date | B10: 46255
A11: Framework | B11: IFRS Accounting Standards as endorsed in Saudi Arabia
A13: B. Understanding the Entity
A14: Business model | B14: Retail (including online sales) and wholesale operations in Saudi Arabia and other GCC countries.
A15: Products and services | B15: Books, office and school supplies, electronics, computers, mobile phones, accessories, toys, arts and crafts, and related services.
A16: Key public-data context | B16: 2025 revenue was SAR 11,449,790 thousand; 2025 profit before zakat and income tax was SAR 1,077,357 thousand.
A17: Potential audit focus | B17: Revenue recognition and inventory existence/valuation are highlighted as key audit areas in the 2025 independent auditor’s report.
A20: C. Preliminary Analytical Procedures
A21: Metric | B21: 2024 | C21: 2025 | D21: Change | E21: Comment | F21: Source / status
A22: Revenue | B22: 10906512 | C22: 11449790 | D22: =(C22-B22)/B22 -> 0.049812259 | E22: Growth calculated from Saudi Exchange financial summary | F22: Saudi Exchange company profile; reported
A23: Profit before zakat and tax | B23: 1004520 | C23: 1077357 | D23: =(C23-B23)/B23 -> 0.072509258 | E23: Growth calculated from Saudi Exchange financial summary | F23: Saudi Exchange company profile; reported
A24: Gross inventory | B24: 2000000 | C24: 1940000 | D24: =(C24-B24)/B24 -> -0.03 | E24: Gross inventory disclosed in audited financial statements | F24: 2025 audited FS, KAM / Note 5; reported
A28: D. Scope, Risks and Planned Deliverables
A29: Scope | B29: Revenue recognition, inventory existence and valuation, selected risks, analytical procedures, and illustrative substantive testing.
A30: Risk hypotheses | B30: Potential revenue cut-off/occurrence risk; potential inventory quantity, cost, and obsolescence risk.
A31: Planned workpapers | B31: Risk assessment, materiality, simulated revenue testing, simulated inventory testing, findings register, and audit summary.
A32: Evidence limitation | B32: Transaction-level records and supporting documents are fictional and are not Jarir records.

Sheet 02_Risk_Assessment
A1: Jarir Audit Simulation 2025 — Risk Assessment
A2: Educational external audit simulation | Jarir Marketing Company | Amounts in SAR '000 unless stated
A4: Risk ID | B4: Area | C4: Risk description | D4: Rationale / source | E4: Assertion | F4: Inherent risk | G4: Control risk | H4: Overall risk | I4: Significant risk? | J4: Planned response | K4: Related worksheet | L4: Status
A5: R-01 | B5: Revenue | C5: Revenue may be recorded in the wrong period, especially around year-end. | D5: Revenue recognition is a key audit matter; cash sales and high transaction volume increase cut-off risk. | E5: Cut-off; occurrence | F5: High | G5: Medium | H5: High | I5: Yes | J5: Test transactions before/after year-end; agree dates to illustrative fulfillment evidence. | K5: 04_Revenue_Testing | L5: Completed
A6: R-02 | B6: Revenue | C6: Recorded revenue may not agree to supporting documentation. | D6: Revenue is a key performance measure and includes retail, wholesale and e-commerce. | E6: Accuracy; occurrence | F6: Medium | G6: Medium | H6: Medium | I6: No | J6: Vouch sample amounts to simulated invoices and ledger amounts. | K6: 04_Revenue_Testing | L6: Completed
A7: R-03 | B7: Inventory | C7: Recorded quantities may differ from physical quantities. | D7: Multiple stores/warehouses and high transaction volumes create existence/completeness exposure. | E7: Existence; completeness | F7: High | G7: Medium | H7: High | I7: Yes | J7: Compare recorded quantities to illustrative count quantities; investigate differences. | K7: 05_Inventory_Testing | L7: Completed
A8: R-04 | B8: Inventory | C8: Inventory may be misstated due to costing or slow-moving items. | D8: The audited report discloses a slow-moving inventory provision and significant management judgment. | E8: Valuation and allocation | F8: High | G8: Medium | H8: High | I8: Yes | J8: Recalculate values and flag items with potential obsolescence indicators. | K8: 05_Inventory_Testing | L8: Completed
A9: R-05 | B9: Inventory | C9: Purchases/dispatches around year-end may be recorded in the wrong period. | D9: Retail inventory is exposed to cut-off around reporting date. | E9: Cut-off; completeness | F9: Medium | G9: Medium | H9: Medium | I9: No | J9: Inspect illustrative receipts and dispatches around 31 December. | K9: 05_Inventory_Testing | L9: Completed

Sheet 03_Materiality
A1: Jarir Audit Simulation 2025 — Materiality
A2: Educational external audit simulation | Jarir Marketing Company | Amounts in SAR '000 unless stated
A4: A. Benchmark Selection
A5: Selected benchmark | B5: Profit before zakat and income tax
A6: Benchmark amount | B6: 1077357
A7: Unit | B7: SAR '000
A8: Rationale | B8: PBT is selected for this educational model because users may focus on profitability and the entity is a profitable listed retailer. The percentage is an illustrative planning assumption, not a universal rule.
A11: B. Threshold Calculations
A12: Threshold | B12: Formula / assumption | C12: Amount (SAR '000) | D12: Use in simulation
A13: Overall materiality | B13: Benchmark × 5.0% | C13: =B6*B14 -> 53867.85 | D13: Overall planning threshold
A14: Performance materiality | B14: 0.05 | C14: =C13*B15 -> 40400.888 | D14: Lower threshold for audit procedures
A15: Clearly trivial threshold | B15: 0.75 | C15: =C13*B16 -> 2693.3925 | D15: Items below this are ordinarily clearly trivial in this simulation
B16: 0.05
A20: C. Source and Application Notes
A21: • All figures are in SAR thousands unless stated otherwise.
A22: • Actual benchmark is sourced from the Saudi Exchange financial summary for Jarir (year ended 31 December 2025).
A23: • Percentages are explicit educational assumptions.
A24: • Testing sheets link to these thresholds rather than retyping them.

Sheet 04_Revenue_Testing
A1: Jarir Audit Simulation 2025 — Revenue Testing
A2: Educational external audit simulation | Jarir Marketing Company | Amounts in SAR '000 unless stated
A4: A. Revenue Background
A5: Reported revenue 2025 | B5: 11449790
A6: Reported revenue 2024 | B6: 10906512
A7: Revenue growth | B7: =B5/B6-1 -> 0.049812259
A8: Revenue recognition policy | B8: Revenue is recognized under IFRS 15 when control of goods or services transfers to the customer; the audited report identifies revenue recognition as a key audit matter.
A9: Materiality reference | B9: ='03_Materiality'!C13 -> 53867.85
A10: Data classification | B10: Reported totals are public financial information. The transaction sample below is simulated for education only.
A13: B. Illustrative Revenue Sample — Fictional Transactions
A14: Sample ID | B14: Transaction ID | C14: Transaction date | D14: Invoice date | E14: Invoice no. | F14: Customer ref. | G14: Description | H14: Invoice amount | I14: Ledger amount | J14: Fulfillment date | K14: Recognition date | L14: Credit note / return | M14: Support status | N14: Difference | O14: Test result | P14: Exception description | Q14: Audit conclusion | R14: Reviewer notes
A15: REV-01 | B15: SIM-R-001 | C15: 2025-12-05 | D15: 2025-12-05 | E15: SIM-INV-001 | F15: SIM-CUST-001 | G15: Laptop accessories bundle | H15: 12500 | I15: 12500 | J15: 2025-12-06 | K15: 2025-12-06 | L15: None | M15: Complete | N15: =I15-H15 -> 0 | O15: =IF(M15="Incomplete","Requires Follow-up",IF(OR(ABS(N15)>0,LEFT(K15,4)<>"2025"),"Exception Identified","No Exception")) -> No Exception | P15: None | Q15: No exception identified | R15: Illustrative only
A16: REV-02 | B16: SIM-R-002 | C16: 2025-12-12 | D16: 2025-12-12 | E16: SIM-INV-002 | F16: SIM-CUST-002 | G16: School supplies order | H16: 8400 | I16: 8400 | J16: 2025-12-13 | K16: 2025-12-13 | L16: None | M16: Complete | N16: =I16-H16 -> 0 | O16: =IF(M16="Incomplete","Requires Follow-up",IF(OR(ABS(N16)>0,LEFT(K16,4)<>"2025"),"Exception Identified","No Exception")) -> No Exception | P16: None | Q16: No exception identified | R16: Illustrative only
A17: REV-03 | B17: SIM-R-003 | C17: 2025-12-20 | D17: 2025-12-20 | E17: SIM-INV-003 | F17: SIM-CUST-003 | G17: Mobile phone sale | H17: 32900 | I17: 32900 | J17: 2025-12-20 | K17: 2025-12-20 | L17: None | M17: Complete | N17: =I17-H17 -> 0 | O17: =IF(M17="Incomplete","Requires Follow-up",IF(OR(ABS(N17)>0,LEFT(K17,4)<>"2025"),"Exception Identified","No Exception")) -> No Exception | P17: None | Q17: No exception identified | R17: Illustrative only
A18: REV-04 | B18: SIM-R-004 | C18: 2025-12-28 | D18: 2025-12-28 | E18: SIM-INV-004 | F18: SIM-CUST-004 | G18: Printer and toner | H18: 15600 | I18: 15400 | J18: 2025-12-29 | K18: 2025-12-29 | L18: None | M18: Complete | N18: =I18-H18 -> -200 | O18: =IF(M18="Incomplete","Requires Follow-up",IF(OR(ABS(N18)>0,LEFT(K18,4)<>"2025"),"Exception Identified","No Exception")) -> Exception Identified | P18: Amount differs by SAR 200 | Q18: Potential amount discrepancy; investigate | R18: Illustrative only
A19: REV-05 | B19: SIM-R-005 | C19: 2025-12-30 | D19: 2025-12-30 | E19: SIM-INV-005 | F19: SIM-CUST-005 | G19: Books and publications | H19: 6200 | I19: 6200 | J19: 2026-01-02 | K19: 2026-01-02 | L19: None | M19: Complete | N19: =I19-H19 -> 0 | O19: =IF(M19="Incomplete","Requires Follow-up",IF(OR(ABS(N19)>0,LEFT(K19,4)<>"2025"),"Exception Identified","No Exception")) -> Exception Identified | P19: Fulfilled after year-end; recognition date is 2026-01-02 | Q19: Potential cut-off exception; obtain policy/evidence | R19: Illustrative only
A20: REV-06 | B20: SIM-R-006 | C20: 2025-12-31 | D20: 2025-12-31 | E20: SIM-INV-006 | F20: SIM-CUST-006 | G20: Tablet device | H20: 27900 | I20: 27900 | J20: 2025-12-31 | K20: 2025-12-31 | L20: None | M20: Complete | N20: =I20-H20 -> 0 | O20: =IF(M20="Incomplete","Requires Follow-up",IF(OR(ABS(N20)>0,LEFT(K20,4)<>"2025"),"Exception Identified","No Exception")) -> No Exception | P20: None | Q20: No exception identified | R20: Illustrative only
A21: REV-07 | B21: SIM-R-007 | C21: 2025-11-14 | D21: 2025-11-14 | E21: SIM-INV-007 | F21: SIM-CUST-007 | G21: Office furniture | H21: 18100 | I21: 18100 | J21: 2025-11-15 | K21: 2025-11-15 | L21: None | M21: Complete | N21: =I21-H21 -> 0 | O21: =IF(M21="Incomplete","Requires Follow-up",IF(OR(ABS(N21)>0,LEFT(K21,4)<>"2025"),"Exception Identified","No Exception")) -> No Exception | P21: None | Q21: No exception identified | R21: Illustrative only
A22: REV-08 | B22: SIM-R-008 | C22: 2025-10-18 | D22: 2025-10-18 | E22: SIM-INV-008 | F22: SIM-CUST-008 | G22: Educational toys | H22: 9700 | I22: 9700 | J22: 2025-10-18 | K22: 2025-10-18 | L22: None | M22: Complete | N22: =I22-H22 -> 0 | O22: =IF(M22="Incomplete","Requires Follow-up",IF(OR(ABS(N22)>0,LEFT(K22,4)<>"2025"),"Exception Identified","No Exception")) -> No Exception | P22: None | Q22: No exception identified | R22: Illustrative only
A23: REV-09 | B23: SIM-R-009 | C23: 2025-12-22 | D23: 2025-12-22 | E23: SIM-INV-009 | F23: SIM-CUST-009 | G23: Wireless headphones | H23: 11400 | I23: 11400 | J23: 2025-12-23 | K23: 2025-12-23 | L23: None | M23: Incomplete | N23: =I23-H23 -> 0 | O23: =IF(M23="Incomplete","Requires Follow-up",IF(OR(ABS(N23)>0,LEFT(K23,4)<>"2025"),"Exception Identified","No Exception")) -> Requires Follow-up | P23: Delivery evidence missing | Q23: Documentation exception; request fulfillment evidence | R23: Illustrative only
A24: REV-10 | B24: SIM-R-010 | C24: 2025-09-30 | D24: 2025-09-30 | E24: SIM-INV-010 | F24: SIM-CUST-010 | G24: Computer monitor | H24: 13500 | I24: 13500 | J24: 2025-10-01 | K24: 2025-10-01 | L24: None | M24: Complete | N24: =I24-H24 -> 0 | O24: =IF(M24="Incomplete","Requires Follow-up",IF(OR(ABS(N24)>0,LEFT(K24,4)<>"2025"),"Exception Identified","No Exception")) -> No Exception | P24: None | Q24: No exception identified | R24: Illustrative only
A25: REV-11 | B25: SIM-R-011 | C25: 2025-12-31 | D25: 2025-12-31 | E25: SIM-INV-011 | F25: SIM-CUST-011 | G25: Smart TV | H25: 22400 | I25: 22400 | J25: 2025-12-31 | K25: 2025-12-31 | L25: None | M25: Complete | N25: =I25-H25 -> 0 | O25: =IF(M25="Incomplete","Requires Follow-up",IF(OR(ABS(N25)>0,LEFT(K25,4)<>"2025"),"Exception Identified","No Exception")) -> No Exception | P25: None | Q25: No exception identified | R25: Illustrative only
A26: REV-12 | B26: SIM-R-012 | C26: 2025-12-31 | D26: 2025-12-31 | E26: SIM-INV-012 | F26: SIM-CUST-012 | G26: Digital card bundle | H26: 4500 | I26: 4500 | J26: 2025-12-31 | K26: 2025-12-31 | L26: None | M26: Complete | N26: =I26-H26 -> 0 | O26: =IF(M26="Incomplete","Requires Follow-up",IF(OR(ABS(N26)>0,LEFT(K26,4)<>"2025"),"Exception Identified","No Exception")) -> No Exception | P26: None | Q26: No exception identified | R26: Illustrative only
A29: C. Revenue Testing Results
A30: Transactions tested | B30: =COUNTA(A15:A26) -> 12
A31: No-exception items | B31: =COUNTIF(O15:O26,"No Exception") -> 9
A32: Exceptions / follow-up items | B32: =COUNTIF(O15:O26,"Exception Identified")+COUNTIF(O15:O26,"Requires Follow-up") -> 3
A33: Total identified amount difference | B33: =SUM(N15:N26) -> -200
A34: Conclusion | B34: The sample includes illustrative exceptions and documentation limitations. It cannot be extrapolated to Jarir’s full revenue population.

Sheet 05_Inventory_Testing
A1: Jarir Audit Simulation 2025 — Inventory Testing
A2: Educational external audit simulation | Jarir Marketing Company | Amounts in SAR '000 unless stated
A4: A. Inventory Background
A5: Gross inventory 2025 | B5: 1940000
A6: Slow-moving provision 2025 | B6: 228000
A7: Net inventory (derived) | B7: =B5-B6 -> 1712000
A8: Gross inventory 2024 | B8: 2000000
A9: Slow-moving provision 2024 | B9: 208000
A10: Valuation policy | B10: Inventories are carried at the lower of cost and net realizable value. The 2025 audited report highlights existence and valuation of inventories as a key audit matter.
A11: Materiality reference | B11: ='03_Materiality'!C13 -> 53867.85
A12: Data classification | B12: Balances and policy are reported public information. The item-level sample below is fictional and illustrative.
A15: B. Illustrative Inventory Sample — Fictional Items
A16: Item ID | B16: Fictional SKU | C16: Description | D16: Recorded qty | E16: Count qty | F16: Qty difference | G16: Unit cost | H16: Recorded value | I16: Recalculated value | J16: Value difference | K16: Condition | L16: Obsolescence indicator | M16: Evidence status | N16: Test result | O16: Exception description | P16: Recommended follow-up | Q16: Conclusion
A17: INV-01 | B17: SIM-SKU-001 | C17: Notebook set | D17: 100 | E17: 100 | F17: =D17-E17 -> 0 | G17: 25 | H17: =D17*G17 -> 2500 | I17: =E17*G17 -> 2500 | J17: =H17-I17 -> 0 | K17: Good | L17: None | M17: Complete | N17: =IF(M17="Incomplete","Requires Follow-up",IF(OR(ABS(F17)>0,ABS(J17)>0,L17<>"None",K17="Damaged"),"Exception Identified","No Exception")) -> No Exception | O17: None | P17: None | Q17: No exception identified
A18: INV-02 | B18: SIM-SKU-002 | C18: Wireless keyboard | D18: 75 | E18: 72 | F18: =D18-E18 -> 3 | G18: 150 | H18: =D18*G18 -> 11250 | I18: =E18*G18 -> 10800 | J18: =H18-I18 -> 450 | K18: Good | L18: None | M18: Complete | N18: =IF(M18="Incomplete","Requires Follow-up",IF(OR(ABS(F18)>0,ABS(J18)>0,L18<>"None",K18="Damaged"),"Exception Identified","No Exception")) -> Exception Identified | O18: Quantity differs by 3 units | P18: Reperform count and trace movements | Q18: Potential quantity exception
A19: INV-03 | B19: SIM-SKU-003 | C19: Tablet case | D19: 50 | E19: 50 | F19: =D19-E19 -> 0 | G19: 80 | H19: =D19*G19 -> 4000 | I19: =E19*G19 -> 4000 | J19: =H19-I19 -> 0 | K19: Good | L19: None | M19: Complete | N19: =IF(M19="Incomplete","Requires Follow-up",IF(OR(ABS(F19)>0,ABS(J19)>0,L19<>"None",K19="Damaged"),"Exception Identified","No Exception")) -> No Exception | O19: None | P19: None | Q19: No exception identified
A20: INV-04 | B20: SIM-SKU-004 | C20: Previous-generation tablet | D20: 30 | E20: 30 | F20: =D20-E20 -> 0 | G20: 900 | H20: =D20*G20 -> 27000 | I20: =E20*G20 -> 27000 | J20: =H20-I20 -> 0 | K20: Fair | L20: Potential slow-moving | M20: Complete | N20: =IF(M20="Incomplete","Requires Follow-up",IF(OR(ABS(F20)>0,ABS(J20)>0,L20<>"None",K20="Damaged"),"Exception Identified","No Exception")) -> Exception Identified | O20: Potential valuation review | P20: Review aging and NRV support | Q20: Potential valuation issue
A21: INV-05 | B21: SIM-SKU-005 | C21: Printer cartridge | D21: 40 | E21: 40 | F21: =D21-E21 -> 0 | G21: 220 | H21: =D21*G21 -> 8800 | I21: =E21*G21 -> 8800 | J21: =H21-I21 -> 0 | K21: Good | L21: None | M21: Complete | N21: =IF(M21="Incomplete","Requires Follow-up",IF(OR(ABS(F21)>0,ABS(J21)>0,L21<>"None",K21="Damaged"),"Exception Identified","No Exception")) -> No Exception | O21: None | P21: None | Q21: No exception identified
A22: INV-06 | B22: SIM-SKU-006 | C22: Smartphone accessory | D22: 60 | E22: 60 | F22: =D22-E22 -> 0 | G22: 65 | H22: =D22*G22 -> 3900 | I22: =E22*G22 -> 3900 | J22: =H22-I22 -> 0 | K22: Good | L22: None | M22: Complete | N22: =IF(M22="Incomplete","Requires Follow-up",IF(OR(ABS(F22)>0,ABS(J22)>0,L22<>"None",K22="Damaged"),"Exception Identified","No Exception")) -> No Exception | O22: None | P22: None | Q22: No exception identified
A23: INV-07 | B23: SIM-SKU-007 | C23: Bluetooth speaker | D23: 25 | E23: 25 | F23: =D23-E23 -> 0 | G23: 300 | H23: =D23*G23 -> 7500 | I23: =E23*G23 -> 7500 | J23: =H23-I23 -> 0 | K23: Damaged | L23: Potential write-down | M23: Incomplete | N23: =IF(M23="Incomplete","Requires Follow-up",IF(OR(ABS(F23)>0,ABS(J23)>0,L23<>"None",K23="Damaged"),"Exception Identified","No Exception")) -> Requires Follow-up | O23: Condition evidence incomplete | P23: Obtain inspection and NRV evidence | Q23: Requires follow-up
A24: INV-08 | B24: SIM-SKU-008 | C24: English books bundle | D24: 120 | E24: 120 | F24: =D24-E24 -> 0 | G24: 45 | H24: =D24*G24 -> 5400 | I24: =E24*G24 -> 5400 | J24: =H24-I24 -> 0 | K24: Good | L24: None | M24: Complete | N24: =IF(M24="Incomplete","Requires Follow-up",IF(OR(ABS(F24)>0,ABS(J24)>0,L24<>"None",K24="Damaged"),"Exception Identified","No Exception")) -> No Exception | O24: None | P24: None | Q24: No exception identified
A25: INV-09 | B25: SIM-SKU-009 | C25: Gaming controller | D25: 18 | E25: 18 | F25: =D25-E25 -> 0 | G25: 280 | H25: =D25*G25 -> 5040 | I25: =E25*G25 -> 5040 | J25: =H25-I25 -> 0 | K25: Good | L25: None | M25: Complete | N25: =IF(M25="Incomplete","Requires Follow-up",IF(OR(ABS(F25)>0,ABS(J25)>0,L25<>"None",K25="Damaged"),"Exception Identified","No Exception")) -> No Exception | O25: None | P25: None | Q25: No exception identified
A26: INV-10 | B26: SIM-SKU-010 | C26: Desk lamp | D26: 35 | E26: 35 | F26: =D26-E26 -> 0 | G26: 110 | H26: =D26*G26 -> 3850 | I26: =E26*G26 -> 3850 | J26: =H26-I26 -> 0 | K26: Good | L26: None | M26: Complete | N26: =IF(M26="Incomplete","Requires Follow-up",IF(OR(ABS(F26)>0,ABS(J26)>0,L26<>"None",K26="Damaged"),"Exception Identified","No Exception")) -> No Exception | O26: None | P26: None | Q26: No exception identified
A27: INV-11 | B27: SIM-SKU-011 | C27: Educational kit | D27: 22 | E27: 22 | F27: =D27-E27 -> 0 | G27: 190 | H27: =D27*G27 -> 4180 | I27: =E27*G27 -> 4180 | J27: =H27-I27 -> 0 | K27: Good | L27: None | M27: Complete | N27: =IF(M27="Incomplete","Requires Follow-up",IF(OR(ABS(F27)>0,ABS(J27)>0,L27<>"None",K27="Damaged"),"Exception Identified","No Exception")) -> No Exception | O27: None | P27: None | Q27: No exception identified
A28: INV-12 | B28: SIM-SKU-012 | C28: Monitor stand | D28: 45 | E28: 45 | F28: =D28-E28 -> 0 | G28: 130 | H28: =D28*G28 -> 5850 | I28: =E28*G28 -> 5850 | J28: =H28-I28 -> 0 | K28: Good | L28: None | M28: Complete | N28: =IF(M28="Incomplete","Requires Follow-up",IF(OR(ABS(F28)>0,ABS(J28)>0,L28<>"None",K28="Damaged"),"Exception Identified","No Exception")) -> No Exception | O28: None | P28: None | Q28: No exception identified
A31: C. Inventory Testing Results
A32: Items tested | B32: =COUNTA(A17:A28) -> 12
A33: Items without exception | B33: =COUNTIF(N17:N28,"No Exception") -> 9
A34: Exceptions / follow-up items | B34: =COUNTIF(N17:N28,"Exception Identified")+COUNTIF(N17:N28,"Requires Follow-up") -> 3
A35: Total illustrative value difference | B35: =SUM(J17:J28) -> 450
A36: Conclusion | B36: Illustrative discrepancies require follow-up in a real engagement; they are not confirmed Jarir misstatements.

Sheet 06_Audit_Findings
A1: Jarir Audit Simulation 2025 — Audit Findings Register
A2: Educational external audit simulation | Jarir Marketing Company | Amounts in SAR '000 unless stated
A4: Finding ID | B4: Procedure | C4: Account | D4: Condition | E4: Criterion / policy | F4: Illustrative cause | G4: Potential impact | H4: Overall materiality comparison | I4: Risk implication | J4: Recommended action | K4: Simulated management response | L4: Status | M4: Conclusion | N4: Reference
A5: F-01 | B5: REV-01 / REV-02 | C5: Revenue | D5: Ledger amount exceeds simulated invoice by SAR 200. | E5: Amount should agree to supporting evidence. | F5: Illustrative data entry error. | G5: 200 | H5: =IF(G5=0,"No quantified amount",IF(G5<='03_Materiality'!C15,"Below performance materiality",IF(G5<='03_Materiality'!C13,"Below overall materiality","Above overall materiality"))) -> Above overall materiality | I5: May indicate need for reconciliation. | J5: Investigate source and correct if confirmed. | K5: Not provided — simulation only. | L5: Requires Follow-up | M5: Unresolved illustrative difference. | N5: 04_Revenue_Testing REV-04
A6: F-02 | B6: REV-02 | C6: Revenue | D6: Simulated fulfillment and recognition occur after 31 December for a 30 December invoice. | E6: Recognize revenue when control transfers under IFRS 15. | F6: Illustrative cut-off scenario. | G6: 0 | H6: =IF(G6=0,"No quantified amount",IF(G6<='03_Materiality'!C15,"Below performance materiality",IF(G6<='03_Materiality'!C13,"Below overall materiality","Above overall materiality"))) -> Above overall materiality | I6: Potential cut-off risk. | J6: Obtain fulfillment evidence and assess recognition date. | K6: Not provided — simulation only. | L6: Requires Follow-up | M6: Potential cut-off exception; not a confirmed misstatement. | N6: 04_Revenue_Testing REV-05
A7: F-03 | B7: REV-01 | C7: Revenue | D7: Delivery evidence is missing for one simulated transaction. | E7: Sufficient appropriate audit evidence is required. | F7: Illustrative documentation gap. | G7: 0 | H7: =IF(G7=0,"No quantified amount",IF(G7<='03_Materiality'!C15,"Below performance materiality",IF(G7<='03_Materiality'!C13,"Below overall materiality","Above overall materiality"))) -> Above overall materiality | I7: Evidence limitation. | J7: Request delivery/fulfillment evidence; do not infer misstatement from absence alone. | K7: Not provided — simulation only. | L7: Requires Follow-up | M7: Unresolved evidence limitation. | N7: 04_Revenue_Testing REV-09
A8: F-04 | B8: INV-01 | C8: Inventory | D8: Illustrative count differs from recorded quantity by 3 units. | E8: Recorded quantities should reconcile to count evidence. | F8: Illustrative counting or recording error. | G8: 450 | H8: =IF(G8=0,"No quantified amount",IF(G8<='03_Materiality'!C15,"Below performance materiality",IF(G8<='03_Materiality'!C13,"Below overall materiality","Above overall materiality"))) -> Above overall materiality | I8: Potential existence/completeness risk. | J8: Reperform count and trace inventory movements. | K8: Not provided — simulation only. | L8: Requires Follow-up | M8: Potential quantity exception. | N8: 05_Inventory_Testing INV-02
A9: F-05 | B9: INV-03 | C9: Inventory | D9: One simulated item is damaged and may require NRV review. | E9: Inventory is carried at lower of cost and NRV. | F9: Illustrative condition issue. | G9: 0 | H9: =IF(G9=0,"No quantified amount",IF(G9<='03_Materiality'!C15,"Below performance materiality",IF(G9<='03_Materiality'!C13,"Below overall materiality","Above overall materiality"))) -> Above overall materiality | I9: Potential valuation risk. | J9: Obtain condition and NRV evidence; assess provision. | K9: Not provided — simulation only. | L9: Requires Follow-up | M9: Potential valuation issue; no adjustment concluded. | N9: 05_Inventory_Testing INV-07
A10: F-06 | B10: INV-03 | C10: Inventory | D10: One simulated item is flagged as potentially slow-moving. | E10: Inventory is carried at the lower of cost and net realizable value; aging and NRV evidence are relevant. | F10: Illustrative aging indicator. | G10: 0 | H10: =IF(G10=0,"No quantified amount",IF(G10<='03_Materiality'!C15,"Below performance materiality",IF(G10<='03_Materiality'!C13,"Below overall materiality","Above overall materiality"))) -> Above overall materiality | I10: Potential valuation risk. | J10: Review aging, sell-through, vendor return rights, and NRV support. | K10: Not provided — simulation only. | L10: Requires Follow-up | M10: Potential valuation issue; no adjustment concluded. | N10: 05_Inventory_Testing INV-04

Sheet 07_Audit_Summary
A1: Jarir Audit Simulation 2025 — Executive Summary
A2: Educational external audit simulation | Jarir Marketing Company | Amounts in SAR '000 unless stated
A4: A. Engagement Overview
A5: Entity | B5: Jarir Marketing Company (Jarir Bookstore)
A6: Reporting period | B6: Year ended 31 December 2025
A7: Scope | B7: Revenue recognition and inventory existence/valuation, supported by planning, risk assessment, materiality, and illustrative substantive testing.
A8: Nature | B8: Educational simulation only; no actual audit engagement was performed.
A11: B. Key Metrics
A12: Metric | B12: Value | C12: Source / linked worksheet
A13: Revenue growth | B13: ='04_Revenue_Testing'!B7 -> 0.049812259 | C13: 04_Revenue_Testing
A14: Overall materiality | B14: ='03_Materiality'!C13 -> 53867.85 | C14: 03_Materiality
A15: Performance materiality | B15: ='03_Materiality'!C14 -> 40400.888 | C15: 03_Materiality
A16: Clearly trivial threshold | B16: ='03_Materiality'!C15 -> 2693.3925 | C16: 03_Materiality
A17: Revenue transactions tested | B17: ='04_Revenue_Testing'!B30 -> 12 | C17: 04_Revenue_Testing
A18: Inventory items tested | B18: ='05_Inventory_Testing'!B32 -> 12 | C18: 05_Inventory_Testing
A19: Findings logged | B19: =COUNTA('06_Audit_Findings'!A5:A10) -> 6 | C19: 06_Audit_Findings
A22: C. Simulation Conclusion
A23: The documented simulation identified illustrative revenue and inventory exceptions requiring follow-up, but the amounts and evidence are fictional at the transaction/item level. The procedures do not support an opinion on Jarir’s actual financial statements, and no audit opinion is issued. In a real engagement, the next steps would include obtaining source documents, reconciling exceptions, assessing aggregation, and evaluating the effect on the financial statements.
A28: D. Key Recommendations
A29: • Complete cut-off testing around year-end with actual fulfillment evidence.
A30: • Reconcile revenue exceptions to source systems and investigate differences.
A31: • Attend/observe inventory counts and test quantity movements.
A32: • Review slow-moving inventory provisions using aging and NRV evidence.
A33: • Document unresolved items and consider aggregate impact against materiality.
